rmskin_builder-2.0.3.dist-info/METADATA
rmskin_builder-2.0.3.dist-info/WHEEL
rmskin_builder-2.0.3.dist-info/entry_points.txt
rmskin_builder-2.0.3.dist-info/licenses/LICENSE
rmskin_builder/__init__.py
rmskin_builder/__init__.pyi
rmskin_builder/py.typed
rmskin_builder/rmskin_builder.pypy311-pp73-x86-linux-gnu.so
rmskin_builder-2.0.3.dist-info/RECORD
