Metadata-Version: 2.4
Name: rmskin-builder
Version: 2.0.3
Classifier: Development Status :: 5 - Production/Stable
Classifier: Intended Audience :: Developers
Classifier: Topic :: System :: Archiving :: Packaging
Classifier: Programming Language :: Python :: 3
License-File: LICENSE
Summary: A script that will attempt to assemble a validating Rainmeter skin package for quick and easy distribution on Github.
Keywords: rainmeter,rainmeter-skin,packaging
Author-email: Brendan Doherty <2bndy5@gmail.com>
License-Expression: MIT
Requires-Python: >=3.9
Project-URL: source, https://github.com/2bndy5/rmskin-action
Project-URL: tracker, https://github.com/2bndy5/rmskin-action/issues
